BatchEval/__init__.py
BatchEval/report_template_adjust.html
BatchEval/report_template_main.html
BatchEval/report_template_raw.html
BatchEval/BatchEval/BatchEval.py
BatchEval/BatchEval/__init__.py
BatchEval/BatchEval/check_correct.py
BatchEval/BatchEval/check_raw.py
BatchEval/BatchEval/generate_pages.py
BatchEval/external/__init__.py
BatchEval/external/module/__init__.py
BatchEval/external/module/dgi.py
BatchEval/external/module/domain_specific_batch_norm.py
BatchEval/external/module/embed_layer.py
BatchEval/external/module/embed_model.py
BatchEval/external/module/graph_vae.py
BatchEval/external/module/losses.py
BatchEval/external/module/residual_bottleneck.py
BatchEval/external/spatialign/__init__.py
BatchEval/external/spatialign/model.py
BatchEval/external/spatialign/trainer.py
BatchEval/external/utils/__init__.py
BatchEval/external/utils/dataset.py
BatchEval/external/utils/early_stopping.py
BatchEval/external/utils/time_decorator.py
BatchEval/integration/__init__.py
BatchEval/integration/bbknn.py
BatchEval/integration/harmony.py
BatchEval/integration/spatiAlign.py
BatchEval/module/__init__.py
BatchEval/module/classifier.py
BatchEval/module/dataset.py
BatchEval/module/early_stop.py
BatchEval/module/loss.py
BatchEval/module/trainer.py
BatchEval/score/__init__.py
BatchEval/score/get_neighbors.py
BatchEval/score/graph_connectivity.py
BatchEval/score/kbet.py
BatchEval/score/ksim.py
BatchEval/score/lisi.py
BatchEval/score/pcr.py
BatchEval/score/silhouette.py
BatchEval/test/__init__.py
BatchEval/test/cdf_plot.py
BatchEval/test/describe_data.py
BatchEval/test/distribution_fitting.py
BatchEval/test/heatmap.py
BatchEval/test/joint_plot.py
BatchEval/test/kernel_plot.py
BatchEval/test/metric_score.py
BatchEval/test/pca_regression.py
BatchEval/test/qq_plot.py
BatchEval/test/umap_plot.py
BatchEval/test/var_mean_plot.py
BatchEval/test/variance_test.py
BatchEval/utils/__init__.py
BatchEval/utils/check_data.py
BatchEval/utils/generate_palette.py
BatchEval/utils/html_utils.py
BatchEval-2.0.1.dist-info/LICENSE
BatchEval-2.0.1.dist-info/METADATA
BatchEval-2.0.1.dist-info/WHEEL
BatchEval-2.0.1.dist-info/top_level.txt
BatchEval-2.0.1.dist-info/RECORD
