Metadata-Version: 2.1
Name: BatchEval
Version: 2.0.1
Summary: BatchEval: Batch Effects Evaluation Workflow for Multi-batch Dataset Joint Analysis
Home-page: https://github.com/STOmics/BatchEval.git
Author: zhangchao
Author-email: 1623804006@qq.com
Classifier: Programming Language :: Python :: 3
Classifier: License :: OSI Approved :: MIT License
Classifier: Operating System :: OS Independent
Requires-Python: >=3.8
License-File: LICENSE
Requires-Dist: distinctipy >=1.2.2
